skit/__init__.py
skit/_types.py
skit/card.py
skit/deck.py
skit/py.typed
skit/render.py
skit_game-0.1.7.dist-info/METADATA
skit_game-0.1.7.dist-info/WHEEL
skit_game-0.1.7.dist-info/RECORD
