Metadata-Version: 2.4
Name: skit-game
Version: 0.1.7
Summary: A tool for prototyping card games
Project-URL: Homepage, https://github.com/vtbassmatt/skit
Project-URL: Repository, https://github.com/vtbassmatt/skit.git
Author-email: Matt Cooper <vtbassmatt@gmail.com>
Classifier: License :: OSI Approved :: MIT License
Classifier: Topic :: Artistic Software
Classifier: Topic :: Games/Entertainment
Classifier: Topic :: Games/Entertainment :: Board Games
Classifier: Topic :: Multimedia :: Graphics
Requires-Python: >=3.11
Requires-Dist: pillow>=11.1.0
